logstyle/base.py
logstyle-1.0.3.dist-info/LICENSE
logstyle-1.0.3.dist-info/METADATA
logstyle-1.0.3.dist-info/WHEEL
logstyle-1.0.3.dist-info/top_level.txt
logstyle-1.0.3.dist-info/RECORD
