Metadata-Version: 2.1
Name: logstyle
Version: 1.0.3
Summary: Logstyle is simply lightweight, colorful and customizable logging library
Author: Toghrul Mirzayev
Author-email: togrul.mirzoev@gmail.com
Keywords: log,logging,logs,logger,python-log
Classifier: Intended Audience :: Developers
Classifier: License :: OSI Approved :: MIT License
Classifier: Programming Language :: Python :: 3
Classifier: Programming Language :: Python :: 3.7
Classifier: Programming Language :: Python :: 3.8
Classifier: Programming Language :: Python :: 3.9
Classifier: Topic :: Software Development
Requires-Python: >=3.7
License-File: LICENSE
Requires-Dist: PyYAML
Requires-Dist: colorama
